{
  "lang": "te",
  "_note": "Draft stimuli — SLP validation required before clinical use.",
  "items": [
    {
      "id": "te-banana",
      "word": "అరటిపండు",
      "translit": "araṭipaṇḍu",
      "emoji": "🍌",
      "semanticCue": "ఇది ఒక పండు. పొడవు, పసుపు రంగు.",
      "phonologicalCue": "ఇది /అ/ తో ప్రారంభమవుతుంది…",
      "gesture": "అరటిపండు ఒలిచి తినే సంజ్ఞ చూపండి.",
      "gestureEmoji": "🤲",
      "distractorEmojis": ["🍎", "🍇", "🍊"]
    },
    {
      "id": "te-apple",
      "word": "యాపిల్",
      "translit": "yāpil",
      "emoji": "🍎",
      "semanticCue": "ఇది ఒక పండు. గుండ్రంగా ఉండి ఎరుపు.",
      "phonologicalCue": "ఇది /యా/ తో ప్రారంభమవుతుంది…",
      "gesture": "ఒక చేతిలో పట్టి కొరికే సంజ్ఞ చూపండి.",
      "gestureEmoji": "🤏",
      "distractorEmojis": ["🍌", "🍊", "🍇"]
    },
    {
      "id": "te-water",
      "word": "నీళ్ళు",
      "translit": "nīḷḷu",
      "emoji": "💧",
      "semanticCue": "దాహం వేసినప్పుడు తాగుతారు.",
      "phonologicalCue": "ఇది /నీ/ తో ప్రారంభమవుతుంది…",
      "gesture": "చేతిని నోటికి ఎత్తి తాగే సంజ్ఞ చూపండి.",
      "gestureEmoji": "🥤",
      "distractorEmojis": ["🍵", "🥛", "🧃"]
    },
    {
      "id": "te-cup",
      "word": "కప్పు",
      "translit": "kappu",
      "emoji": "☕",
      "semanticCue": "దీనిలో తాగుతారు.",
      "phonologicalCue": "ఇది /క/ తో ప్రారంభమవుతుంది…",
      "gesture": "కప్పు పిడిని పట్టి పైకి ఎత్తండి.",
      "gestureEmoji": "✋",
      "distractorEmojis": ["🍽️", "🥄", "🍴"]
    },
    {
      "id": "te-chair",
      "word": "కుర్చీ",
      "translit": "kurchī",
      "emoji": "🪑",
      "semanticCue": "దీనిపై కూర్చుంటారు.",
      "phonologicalCue": "ఇది /కు/ తో ప్రారంభమవుతుంది…",
      "gesture": "కూర్చున్నట్లు కొంచెం వంగండి.",
      "gestureEmoji": "🧎",
      "distractorEmojis": ["🛏️", "🪟", "🚪"]
    },
    {
      "id": "te-bed",
      "word": "మంచం",
      "translit": "mancham",
      "emoji": "🛏️",
      "semanticCue": "రాత్రి దీనిపై పడుకుంటారు.",
      "phonologicalCue": "ఇది /మ/ తో ప్రారంభమవుతుంది…",
      "gesture": "చేతులపై తల ఉంచి పడుకునే సంజ్ఞ.",
      "gestureEmoji": "🛌",
      "distractorEmojis": ["🪑", "🛋️", "🚪"]
    },
    {
      "id": "te-dog",
      "word": "కుక్క",
      "translit": "kukka",
      "emoji": "🐕",
      "semanticCue": "ఒక జంతువు. మొరుగుతుంది.",
      "phonologicalCue": "ఇది /కు/ తో ప్రారంభమవుతుంది…",
      "gesture": "తొడ తట్టి పెంపుడు జంతువును పిలవండి.",
      "gestureEmoji": "🐾",
      "distractorEmojis": ["🐈", "🐄", "🐇"]
    },
    {
      "id": "te-tea",
      "word": "టీ",
      "translit": "ṭī",
      "emoji": "🍵",
      "semanticCue": "వేడి పానీయం.",
      "phonologicalCue": "ఇది /టీ/ తో ప్రారంభమవుతుంది…",
      "gesture": "చిన్న కప్పు పట్టి ఊది తాగండి.",
      "gestureEmoji": "🍵",
      "distractorEmojis": ["☕", "🥛", "🧃"]
    },
    {
      "id": "te-book",
      "word": "పుస్తకం",
      "translit": "pustakam",
      "emoji": "📖",
      "semanticCue": "దీన్ని చదువుతారు. పేజీలు ఉంటాయి.",
      "phonologicalCue": "ఇది /పు/ తో ప్రారంభమవుతుంది…",
      "gesture": "రెండు అరచేతులు పుస్తకంలా తెరవండి.",
      "gestureEmoji": "📖",
      "distractorEmojis": ["📱", "📺", "📰"]
    },
    {
      "id": "te-house",
      "word": "ఇల్లు",
      "translit": "illu",
      "emoji": "🏠",
      "semanticCue": "మీరు నివసించే స్థలం.",
      "phonologicalCue": "ఇది /ఇ/ తో ప్రారంభమవుతుంది…",
      "gesture": "తలపై వేళ్ళు కలిపి పైకప్పు చేయండి.",
      "gestureEmoji": "🛖",
      "distractorEmojis": ["🏥", "🏫", "🏪"]
    }
  ]
}
